{
    "data": [
        {
            "underlying": "NIFTY",
            "identifier": "FUTIDXNIFTY28-10-2021XX0.00",
            "instrumentType": "FUTIDX",
            "instrument": "Index Futures",
            "contract": "NIFTY 28-Oct-2021",
            "expiryDate": "28-Oct-2021",
            "optionType": "-",
            "strikePrice": 0,
            "lastPrice": 17708.65,
            "change": 178.45,
            "pChange": 1.02,
            "volume": 5742450,
            "totalTurnover": 101513193516,
            "value": 101513193516,
            "premiumTurnOver": 101513193516,
            "underlyingValue": 17703.6,
            "openInterest": 249239,
            "noOfTrades": 114472,
            "meta": {
                "data": [],
                "msg": "No Data Found"
            }
        },
        {
            "underlying": "NIFTY",
            "identifier": "FUTIDXNIFTY25-11-2021XX0.00",
            "instrumentType": "FUTIDX",
            "instrument": "Index Futures",
            "contract": "NIFTY 25-Nov-2021",
            "expiryDate": "25-Nov-2021",
            "optionType": "-",
            "strikePrice": 0,
            "lastPrice": 17745,
            "change": 179.65,
            "pChange": 1.02,
            "volume": 236500,
            "totalTurnover": 4188613660,
            "value": 4188613660,
            "premiumTurnOver": 4188613660,
            "underlyingValue": 17703.6,
            "openInterest": 12056,
            "noOfTrades": 4721,
            "meta": {
                "data": [],
                "msg": "No Data Found"
            }
        },
        {
            "underlying": "NIFTY",
            "identifier": "FUTIDXNIFTY30-12-2021XX0.00",
            "instrumentType": "FUTIDX",
            "instrument": "Index Futures",
            "contract": "NIFTY 30-Dec-2021",
            "expiryDate": "30-Dec-2021",
            "optionType": "-",
            "strikePrice": 0,
            "lastPrice": 17780,
            "change": 174.85,
            "pChange": 0.99,
            "volume": 72550,
            "totalTurnover": 1287913404.0000002,
            "value": 1287913404.0000002,
            "premiumTurnOver": 1287913404.0000002,
            "underlyingValue": 17703.6,
            "openInterest": 1513,
            "noOfTrades": 1446,
            "meta": {
                "data": [],
                "msg": "No Data Found"
            }
        }
    ],
    "timestamp": "04-Oct-2021 14:29:55",
    "marketStatus": {
        "market": "FO",
        "marketOpenOrClose": "Open",
        "marketCurrentTradingDate": "Oct 04,2021",
        "marketOpenTime": "0915",
        "marketCloseTime": "1530",
        "marketPreviousTradingDate": "Oct 01,2021",
        "marketNextTradingDate": "Oct 05,2021",
        "marketStatusMessage": "Market is Open"
    }
}